cloudflow/__init__.py
cloudflow/cloudflow_model.py
cloudflow/custom_class_mlflow.py
cloudflow/init_logger.py
cloudflow/prepare_env.py
cloudflow-1.0.5.dist-info/LICENSE.txt
cloudflow-1.0.5.dist-info/METADATA
cloudflow-1.0.5.dist-info/WHEEL
cloudflow-1.0.5.dist-info/top_level.txt
cloudflow-1.0.5.dist-info/RECORD
