Metadata-Version: 2.1
Name: cloudflow
Version: 1.0.5
Summary: Cloudflow: A platform to streamline your end-to-end Machine Learning pipeline management
Home-page: https://github.com/SimonLMC/cloudflow/
Author: Simon Le Mouellic
Author-email: simon.lemouellic@outlook.com
License: mit
Project-URL: Documentation, https://github.com/SimonLMC/cloudflow/
Platform: any
Requires-Python: >=3.6
Requires-Dist: mlflow (>=2.0.1)
Requires-Dist: cloudpickle (>=2.0.0)
